sqlalchemy_dremio/__init__.py
sqlalchemy_dremio/base.py
sqlalchemy_dremio/db.py
sqlalchemy_dremio/exceptions.py
sqlalchemy_dremio/flight.py
sqlalchemy_dremio/flight_middleware.py
sqlalchemy_dremio/query.py
sqlalchemy_dremio-3.0.3.dist-info/LICENSE
sqlalchemy_dremio-3.0.3.dist-info/METADATA
sqlalchemy_dremio-3.0.3.dist-info/WHEEL
sqlalchemy_dremio-3.0.3.dist-info/entry_points.txt
sqlalchemy_dremio-3.0.3.dist-info/top_level.txt
sqlalchemy_dremio-3.0.3.dist-info/RECORD
