Metadata-Version: 2.1
Name: sqlalchemy-dremio
Version: 3.0.3
Summary: A SQLAlchemy dialect for Dremio via the Flight interface.
Home-page: https://github.com/narendrans/sqlalchemy_dremio
Author: Naren
Author-email: me@narendran.info
License: Apache Software License
Keywords: sqlalchemy_dremio
Classifier: Development Status :: 5 - Production/Stable
Classifier: Intended Audience :: Developers
Classifier: License :: OSI Approved :: Apache Software License
Classifier: Natural Language :: English
Classifier: Programming Language :: Python :: 3
Classifier: Programming Language :: Python :: 3.7
License-File: LICENSE
Requires-Dist: sqlalchemy (>=1.3.24)
Requires-Dist: pyarrow (>=5.0.0)
